{"id": "crosswords/quick/14920", "number": 14920, "name": "Quick crossword No 14,920", "date": 1520035200000, "webPublicationDate": 1520035202000, "entries": [{"id": "1-across", "number": 1, "humanNumber": "1", "clue": "Decapitate (6)", "direction": "across", "length": 6, "group": ["1-across"], "position": {"x": 1, "y": 0}, "separatorLocations": {}, "solution": "BEHEAD"}, {"id": "4-across", "number": 4, "humanNumber": "4", "clue": "Idiosyncrasy (5)", "direction": "across", "length": 5, "group": ["4-across"], "position": {"x": 8, "y": 0}, "separatorLocations": {}, "solution": "QUIRK"}, {"id": "7-across", "number": 7, "humanNumber": "7", "clue": "Cake-burning king (6)", "direction": "across", "length": 6, "group": ["7-across"], "position": {"x": 0, "y": 2}, "separatorLocations": {}, "solution": "ALFRED"}, {"id": "8-across", "number": 8, "humanNumber": "8", "clue": "Distinctive flag (6)", "direction": "across", "length": 6, "group": ["8-across"], "position": {"x": 7, "y": 2}, "separatorLocations": {}, "solution": "BANNER"}, {"id": "9-across", "number": 9, "humanNumber": "9", "clue": "Game with 18 holes (4)", "direction": "across", "length": 4, "group": ["9-across"], "position": {"x": 0, "y": 4}, "separatorLocations": {}, "solution": "GOLF"}, {"id": "10-across", "number": 10, "humanNumber": "10", "clue": "I must think about this (3,2,3)", "direction": "across", "length": 8, "group": ["10-across"], "position": {"x": 5, "y": 4}, "separatorLocations": {",": [3, 5]}, "solution": "LETMESEE"}, {"id": "12-across", "number": 12, "humanNumber": "12", "clue": "Automatic rifle first produced in the Soviet Union in 1949 (11)", "direction": "across", "length": 11, "group": ["12-across"], "position": {"x": 1, "y": 6}, "separatorLocations": {}, "solution": "KALASHNIKOV"}, {"id": "17-across", "number": 17, "humanNumber": "17", "clue": "Riding event (8)", "direction": "across", "length": 8, "group": ["17-across"], "position": {"x": 0, "y": 8}, "separatorLocations": {}, "solution": "GYMKHANA"}, {"id": "19-across", "number": 19, "humanNumber": "19", "clue": "Something typical (4)", "direction": "across", "length": 4, "group": ["19-across"], "position": {"x": 9, "y": 8}, "separatorLocations": {}, "solution": "NORM"}, {"id": "20-across", "number": 20, "humanNumber": "20", "clue": "Approximately (6)", "direction": "across", "length": 6, "group": ["20-across"], "position": {"x": 0, "y": 10}, "separatorLocations": {}, "solution": "AROUND"}, {"id": "21-across", "number": 21, "humanNumber": "21", "clue": "Fervour (6)", "direction": "across", "length": 6, "group": ["21-across"], "position": {"x": 7, "y": 10}, "separatorLocations": {}, "solution": "ARDOUR"}, {"id": "22-across", "number": 22, "humanNumber": "22", "clue": "Invited (5)", "direction": "across", "length": 5, "group": ["22-across"], "position": {"x": 0, "y": 12}, "separatorLocations": {}, "solution": "ASKED"}, {"id": "23-across", "number": 23, "humanNumber": "23", "clue": "(Of food) served in alcohol and set alight (6)", "direction": "across", "length": 6, "group": ["23-across"], "position": {"x": 6, "y": 12}, "separatorLocations": {}, "solution": "FLAMBE"}, {"id": "1-down", "number": 1, "humanNumber": "1", "clue": "Steer (7)", "direction": "down", "length": 7, "group": ["1-down"], "position": {"x": 1, "y": 0}, "separatorLocations": {}, "solution": "BULLOCK"}, {"id": "2-down", "number": 2, "humanNumber": "2", "clue": "Injurious (7)", "direction": "down", "length": 7, "group": ["2-down"], "position": {"x": 3, "y": 0}, "separatorLocations": {}, "solution": "HARMFUL"}, {"id": "3-down", "number": 3, "humanNumber": "3", "clue": "Region of southern Spain (9)", "direction": "down", "length": 9, "group": ["3-down"], "position": {"x": 5, "y": 0}, "separatorLocations": {}, "solution": "ANDALUSIA"}, {"id": "4-down", "number": 4, "humanNumber": "4", "clue": "Misgiving (5)", "direction": "down", "length": 5, "group": ["4-down"], "position": {"x": 8, "y": 0}, "separatorLocations": {}, "solution": "QUALM"}, {"id": "5-down", "number": 5, "humanNumber": "5", "clue": "French dramatist, leading figure in the theatre of the absurd, d. 1994 (7)", "direction": "down", "length": 7, "group": ["5-down"], "position": {"x": 10, "y": 0}, "separatorLocations": {}, "solution": "IONESCO"}, {"id": "6-down", "number": 6, "humanNumber": "6", "clue": "Nucleus (6)", "direction": "down", "length": 6, "group": ["6-down"], "position": {"x": 12, "y": 0}, "separatorLocations": {}, "solution": "KERNEL"}, {"id": "11-down", "number": 11, "humanNumber": "11", "clue": "In vain (2,2,5)", "direction": "down", "length": 9, "group": ["11-down"], "position": {"x": 7, "y": 4}, "separatorLocations": {",": [2, 4]}, "solution": "TONOAVAIL"}, {"id": "13-down", "number": 13, "humanNumber": "13", "clue": "Wrestling hold (7)", "direction": "down", "length": 7, "group": ["13-down"], "position": {"x": 2, "y": 6}, "separatorLocations": {}, "solution": "ARMLOCK"}, {"id": "14-down", "number": 14, "humanNumber": "14", "clue": "What Richard III would have given for a horse (7)", "direction": "down", "length": 7, "group": ["14-down"], "position": {"x": 9, "y": 6}, "separatorLocations": {}, "solution": "KINGDOM"}, {"id": "15-down", "number": 15, "humanNumber": "15", "clue": "Greenery (7)", "direction": "down", "length": 7, "group": ["15-down"], "position": {"x": 11, "y": 6}, "separatorLocations": {}, "solution": "VERDURE"}, {"id": "16-down", "number": 16, "humanNumber": "16", "clue": "Arboreal lizard (6)", "direction": "down", "length": 6, "group": ["16-down"], "position": {"x": 0, "y": 7}, "separatorLocations": {}, "solution": "IGUANA"}, {"id": "18-down", "number": 18, "humanNumber": "18", "clue": "Perfected (5)", "direction": "down", "length": 5, "group": ["18-down"], "position": {"x": 4, "y": 8}, "separatorLocations": {}, "solution": "HONED"}], "solutionAvailable": true, "dateSolutionAvailable": 1520035200000, "dimensions": {"cols": 13, "rows": 13}, "crosswordType": "quick", "pdf": "https://crosswords-static.guim.co.uk/gdn.quick.20180303.pdf"}