{"id": "crosswords/quick/10796", "number": 10796, "name": "Quick crossword No 10,796", "date": 1102723200000, "webPublicationDate": 1102723200000, "entries": [{"id": "1-across", "number": 1, "humanNumber": "1", "clue": "Die away (4)", "direction": "across", "length": 4, "group": ["1-across"], "position": {"x": 0, "y": 0}, "separatorLocations": {}, "solution": "FADE"}, {"id": "3-across", "number": 3, "humanNumber": "3", "clue": "Mechanism on for, say, three and half minutes? (3,5)", "direction": "across", "length": 8, "group": ["3-across"], "position": {"x": 5, "y": 0}, "separatorLocations": {",": [3]}, "solution": "EGGTIMER"}, {"id": "9-across", "number": 9, "humanNumber": "9", "clue": "Meet formally (7)", "direction": "across", "length": 7, "group": ["9-across"], "position": {"x": 0, "y": 2}, "separatorLocations": {}, "solution": "CONVENE"}, {"id": "10-across", "number": 10, "humanNumber": "10", "clue": "Destiny, of Buddhism and Hinduism (5)", "direction": "across", "length": 5, "group": ["10-across"], "position": {"x": 8, "y": 2}, "separatorLocations": {}, "solution": "KARMA"}, {"id": "11-across", "number": 11, "humanNumber": "11", "clue": "White blood cell fluid (5)", "direction": "across", "length": 5, "group": ["11-across"], "position": {"x": 0, "y": 4}, "separatorLocations": {}, "solution": "LYMPH"}, {"id": "12-across", "number": 12, "humanNumber": "12", "clue": "Herge's adventurer (6)", "direction": "across", "length": 6, "group": ["12-across"], "position": {"x": 6, "y": 4}, "separatorLocations": {}, "solution": "TINTIN"}, {"id": "14-across", "number": 14, "humanNumber": "14", "clue": "Military drill (6-7)", "direction": "across", "length": 13, "group": ["14-across"], "position": {"x": 0, "y": 6}, "separatorLocations": {"-": [6]}, "solution": "SQUAREBASHING"}, {"id": "17-across", "number": 17, "humanNumber": "17", "clue": "Fair game (6)", "direction": "across", "length": 6, "group": ["17-across"], "position": {"x": 1, "y": 8}, "separatorLocations": {}, "solution": "HOOPLA"}, {"id": "19-across", "number": 19, "humanNumber": "19", "clue": "Equip with better weapons (5)", "direction": "across", "length": 5, "group": ["19-across"], "position": {"x": 8, "y": 8}, "separatorLocations": {}, "solution": "REARM"}, {"id": "22-across", "number": 22, "humanNumber": "22", "clue": "Legal proof of innocence (5)", "direction": "across", "length": 5, "group": ["22-across"], "position": {"x": 0, "y": 10}, "separatorLocations": {}, "solution": "ALIBI"}, {"id": "23-across", "number": 23, "humanNumber": "23", "clue": "Cyclonic storm (7)", "direction": "across", "length": 7, "group": ["23-across"], "position": {"x": 6, "y": 10}, "separatorLocations": {}, "solution": "TYPHOON"}, {"id": "24-across", "number": 24, "humanNumber": "24", "clue": "Tree associated with silkworms (8)", "direction": "across", "length": 8, "group": ["24-across"], "position": {"x": 0, "y": 12}, "separatorLocations": {}, "solution": "MULBERRY"}, {"id": "25-across", "number": 25, "humanNumber": "25", "clue": "Indian king or prince (4)", "direction": "across", "length": 4, "group": ["25-across"], "position": {"x": 9, "y": 12}, "separatorLocations": {}, "solution": "RAJA"}, {"id": "1-down", "number": 1, "humanNumber": "1", "clue": "Irresponsible (8)", "direction": "down", "length": 8, "group": ["1-down"], "position": {"x": 0, "y": 0}, "separatorLocations": {}, "solution": "FECKLESS"}, {"id": "2-down", "number": 2, "humanNumber": "2", "clue": "Jeans material (5)", "direction": "down", "length": 5, "group": ["2-down"], "position": {"x": 2, "y": 0}, "separatorLocations": {}, "solution": "DENIM"}, {"id": "4-down", "number": 4, "humanNumber": "4", "clue": "Large portable radio and CD player (6,7)", "direction": "down", "length": 13, "group": ["4-down"], "position": {"x": 6, "y": 0}, "separatorLocations": {",": [6]}, "solution": "GHETTOBLASTER"}, {"id": "5-down", "number": 5, "humanNumber": "5", "clue": "Voucher (5)", "direction": "down", "length": 5, "group": ["5-down"], "position": {"x": 8, "y": 0}, "separatorLocations": {}, "solution": "TOKEN"}, {"id": "6-down", "number": 6, "humanNumber": "6", "clue": "Type of vermouth (7)", "direction": "down", "length": 7, "group": ["6-down"], "position": {"x": 10, "y": 0}, "separatorLocations": {}, "solution": "MARTINI"}, {"id": "7-down", "number": 7, "humanNumber": "7", "clue": "Study (4)", "direction": "down", "length": 4, "group": ["7-down"], "position": {"x": 12, "y": 0}, "separatorLocations": {}, "solution": "READ"}, {"id": "8-down", "number": 8, "humanNumber": "8", "clue": "Breeze (6)", "direction": "down", "length": 6, "group": ["8-down"], "position": {"x": 4, "y": 1}, "separatorLocations": {}, "solution": "ZEPHYR"}, {"id": "13-down", "number": 13, "humanNumber": "13", "clue": "Obsessive self-centredness (8)", "direction": "down", "length": 8, "group": ["13-down"], "position": {"x": 12, "y": 5}, "separatorLocations": {}, "solution": "EGOMANIA"}, {"id": "15-down", "number": 15, "humanNumber": "15", "clue": "Of a wife (7)", "direction": "down", "length": 7, "group": ["15-down"], "position": {"x": 2, "y": 6}, "separatorLocations": {}, "solution": "UXORIAL"}, {"id": "16-down", "number": 16, "humanNumber": "16", "clue": "Military chevron (6)", "direction": "down", "length": 6, "group": ["16-down"], "position": {"x": 8, "y": 6}, "separatorLocations": {}, "solution": "STRIPE"}, {"id": "18-down", "number": 18, "humanNumber": "18", "clue": "Award (5)", "direction": "down", "length": 5, "group": ["18-down"], "position": {"x": 4, "y": 8}, "separatorLocations": {}, "solution": "PRIZE"}, {"id": "20-down", "number": 20, "humanNumber": "20", "clue": "Smell (5)", "direction": "down", "length": 5, "group": ["20-down"], "position": {"x": 10, "y": 8}, "separatorLocations": {}, "solution": "AROMA"}, {"id": "21-down", "number": 21, "humanNumber": "21", "clue": "Between hot and cold (4)", "direction": "down", "length": 4, "group": ["21-down"], "position": {"x": 0, "y": 9}, "separatorLocations": {}, "solution": "WARM"}], "solutionAvailable": true, "dateSolutionAvailable": 1102723200000, "dimensions": {"cols": 13, "rows": 13}, "crosswordType": "quick", "instructions": "Clue 12 across should read \"Herg&eacute;'s adventurer (6)\""}