{"id": "crosswords/quick/14030", "number": 14030, "name": "Quick crossword No 14,030", "date": 1430179200000, "webPublicationDate": 1430175600000, "entries": [{"id": "1-across", "number": 1, "humanNumber": "1", "clue": "Moved unsteadily (7)", "direction": "across", "length": 7, "group": ["1-across"], "position": {"x": 0, "y": 0}, "separatorLocations": {}, "solution": "WOBBLED"}, {"id": "8-across", "number": 8, "humanNumber": "8", "clue": "Gain with effort (7)", "direction": "across", "length": 7, "group": ["8-across"], "position": {"x": 6, "y": 1}, "separatorLocations": {}, "solution": "ACHIEVE"}, {"id": "9-across", "number": 9, "humanNumber": "9", "clue": "Intoxicated (7)", "direction": "across", "length": 7, "group": ["9-across"], "position": {"x": 0, "y": 2}, "separatorLocations": {}, "solution": "DRUNKEN"}, {"id": "10-across", "number": 10, "humanNumber": "10", "clue": "Piano keys (slang) (7)", "direction": "across", "length": 7, "group": ["10-across"], "position": {"x": 6, "y": 3}, "separatorLocations": {}, "solution": "IVORIES"}, {"id": "11-across", "number": 11, "humanNumber": "11", "clue": "Dog-like African carnivore (5)", "direction": "across", "length": 5, "group": ["11-across"], "position": {"x": 0, "y": 4}, "separatorLocations": {}, "solution": "HYENA"}, {"id": "13-across", "number": 13, "humanNumber": "13", "clue": "Kind of three-dimensional images (9)", "direction": "across", "length": 9, "group": ["13-across"], "position": {"x": 4, "y": 5}, "separatorLocations": {}, "solution": "HOLOGRAMS"}, {"id": "15-across", "number": 15, "humanNumber": "15", "clue": "Place of entertainment (9)", "direction": "across", "length": 9, "group": ["15-across"], "position": {"x": 0, "y": 7}, "separatorLocations": {}, "solution": "NIGHTCLUB"}, {"id": "18-across", "number": 18, "humanNumber": "18", "clue": "Encouraged (5)", "direction": "across", "length": 5, "group": ["18-across"], "position": {"x": 8, "y": 8}, "separatorLocations": {}, "solution": "URGED"}, {"id": "21-across", "number": 21, "humanNumber": "21", "clue": "Roll of hair worn at the back of the head (7)", "direction": "across", "length": 7, "group": ["21-across"], "position": {"x": 0, "y": 9}, "separatorLocations": {}, "solution": "CHIGNON"}, {"id": "22-across", "number": 22, "humanNumber": "22", "clue": "Queen of the Fairies (7)", "direction": "across", "length": 7, "group": ["22-across"], "position": {"x": 6, "y": 10}, "separatorLocations": {}, "solution": "TITANIA"}, {"id": "23-across", "number": 23, "humanNumber": "23", "clue": "Take for oneself (7)", "direction": "across", "length": 7, "group": ["23-across"], "position": {"x": 0, "y": 11}, "separatorLocations": {}, "solution": "SNAFFLE"}, {"id": "24-across", "number": 24, "humanNumber": "24", "clue": "Stealing (7)", "direction": "across", "length": 7, "group": ["24-across"], "position": {"x": 6, "y": 12}, "separatorLocations": {}, "solution": "LARCENY"}, {"id": "1-down", "number": 1, "humanNumber": "1", "clue": "Broadness (5)", "direction": "down", "length": 5, "group": ["1-down"], "position": {"x": 0, "y": 0}, "separatorLocations": {}, "solution": "WIDTH"}, {"id": "2-down", "number": 2, "humanNumber": "2", "clue": "Cruel person (5)", "direction": "down", "length": 5, "group": ["2-down"], "position": {"x": 2, "y": 0}, "separatorLocations": {}, "solution": "BRUTE"}, {"id": "3-down", "number": 3, "humanNumber": "3, 5", "clue": " (Moving) very easily and without resistance (4,1,3,5,7,6)", "direction": "down", "length": 13, "group": ["3-down", "5-down"], "position": {"x": 4, "y": 0}, "separatorLocations": {",": [4, 5, 8, 13]}, "solution": "LIKEAHOTKNIFE"}, {"id": "4-down", "number": 4, "humanNumber": "4", "clue": "He did time in a den of lions (6)", "direction": "down", "length": 6, "group": ["4-down"], "position": {"x": 6, "y": 0}, "separatorLocations": {}, "solution": "DANIEL"}, {"id": "5-down", "number": 5, "humanNumber": "5", "clue": "See 3", "direction": "down", "length": 13, "group": ["3-down", "5-down"], "position": {"x": 8, "y": 0}, "separatorLocations": {",": [7]}, "solution": "THROUGHBUTTER"}, {"id": "6-down", "number": 6, "humanNumber": "6", "clue": "Light-sensitive eyeball tissue (6)", "direction": "down", "length": 6, "group": ["6-down"], "position": {"x": 10, "y": 0}, "separatorLocations": {}, "solution": "RETINA"}, {"id": "7-down", "number": 7, "humanNumber": "7", "clue": "Fine animals (6)", "direction": "down", "length": 6, "group": ["7-down"], "position": {"x": 12, "y": 0}, "separatorLocations": {}, "solution": "BEASTS"}, {"id": "12-down", "number": 12, "humanNumber": "12", "clue": "Legendary Himalayan creature (4)", "direction": "down", "length": 4, "group": ["12-down"], "position": {"x": 1, "y": 4}, "separatorLocations": {}, "solution": "YETI"}, {"id": "14-down", "number": 14, "humanNumber": "14", "clue": "Partner (4)", "direction": "down", "length": 4, "group": ["14-down"], "position": {"x": 11, "y": 5}, "separatorLocations": {}, "solution": "MATE"}, {"id": "15-down", "number": 15, "humanNumber": "15", "clue": "Sin etc (anag) (6)", "direction": "down", "length": 6, "group": ["15-down"], "position": {"x": 0, "y": 7}, "separatorLocations": {}, "solution": "NICEST"}, {"id": "16-down", "number": 16, "humanNumber": "16", "clue": "Fretted musical instrument (6)", "direction": "down", "length": 6, "group": ["16-down"], "position": {"x": 2, "y": 7}, "separatorLocations": {}, "solution": "GUITAR"}, {"id": "17-down", "number": 17, "humanNumber": "17", "clue": "Supporting beam over a doorway (6)", "direction": "down", "length": 6, "group": ["17-down"], "position": {"x": 6, "y": 7}, "separatorLocations": {}, "solution": "LINTEL"}, {"id": "19-down", "number": 19, "humanNumber": "19", "clue": "Literary style (5)", "direction": "down", "length": 5, "group": ["19-down"], "position": {"x": 10, "y": 8}, "separatorLocations": {}, "solution": "GENRE"}, {"id": "20-down", "number": 20, "humanNumber": "20", "clue": "Personal journal (5)", "direction": "down", "length": 5, "group": ["20-down"], "position": {"x": 12, "y": 8}, "separatorLocations": {}, "solution": "DIARY"}], "solutionAvailable": true, "dateSolutionAvailable": 1430175600000, "dimensions": {"cols": 13, "rows": 13}, "crosswordType": "quick", "pdf": "http://static.guim.co.uk/crosswords/pdfs/gdn.quick.20150428.pdf"}