{"id": "crosswords/quick/14604", "number": 14604, "name": "Quick crossword No 14,604", "date": 1488153600000, "webPublicationDate": 1488153643000, "entries": [{"id": "1-across", "number": 1, "humanNumber": "1", "clue": "Holiday business \u2014 dire start-out (anag) (7,5)", "direction": "across", "length": 12, "group": ["1-across"], "position": {"x": 1, "y": 0}, "separatorLocations": {",": [7]}, "solution": "TOURISTTRADE"}, {"id": "9-across", "number": 9, "humanNumber": "9", "clue": "Like a sheep (5)", "direction": "across", "length": 5, "group": ["9-across"], "position": {"x": 0, "y": 2}, "separatorLocations": {}, "solution": "OVINE"}, {"id": "10-across", "number": 10, "humanNumber": "10", "clue": "Most egotistical (7)", "direction": "across", "length": 7, "group": ["10-across"], "position": {"x": 6, "y": 2}, "separatorLocations": {}, "solution": "VAINEST"}, {"id": "11-across", "number": 11, "humanNumber": "11", "clue": "Bloody (4)", "direction": "across", "length": 4, "group": ["11-across"], "position": {"x": 0, "y": 4}, "separatorLocations": {}, "solution": "GORY"}, {"id": "12-across", "number": 12, "humanNumber": "12", "clue": "B\u00eate noire (8)", "direction": "across", "length": 8, "group": ["12-across"], "position": {"x": 5, "y": 4}, "separatorLocations": {}, "solution": "ANATHEMA"}, {"id": "14-across", "number": 14, "humanNumber": "14, 5", "clue": " They are hard to say (6-8)", "direction": "across", "length": 6, "group": ["14-across", "5-down"], "position": {"x": 0, "y": 6}, "separatorLocations": {"-": [6]}, "solution": "TONGUE"}, {"id": "15-across", "number": 15, "humanNumber": "15", "clue": "Italian liqueur made from residue of grapes after pressing (6)", "direction": "across", "length": 6, "group": ["15-across"], "position": {"x": 7, "y": 6}, "separatorLocations": {}, "solution": "GRAPPA"}, {"id": "18-across", "number": 18, "humanNumber": "18, 4", "clue": " Practice of moving time forward an hour in spring (8,6)", "direction": "across", "length": 8, "group": ["18-across", "4-down"], "position": {"x": 0, "y": 8}, "separatorLocations": {",": [8]}, "solution": "DAYLIGHT"}, {"id": "20-across", "number": 20, "humanNumber": "20", "clue": "Killer whale (4)", "direction": "across", "length": 4, "group": ["20-across"], "position": {"x": 9, "y": 8}, "separatorLocations": {}, "solution": "ORCA"}, {"id": "22-across", "number": 22, "humanNumber": "22", "clue": "River flowing from Lake Erie into Lake Ontario (7)", "direction": "across", "length": 7, "group": ["22-across"], "position": {"x": 0, "y": 10}, "separatorLocations": {}, "solution": "NIAGARA"}, {"id": "23-across", "number": 23, "humanNumber": "23", "clue": "Bombardment (5)", "direction": "across", "length": 5, "group": ["23-across"], "position": {"x": 8, "y": 10}, "separatorLocations": {}, "solution": "BLITZ"}, {"id": "24-across", "number": 24, "humanNumber": "24", "clue": "Knife once used at breakfast time? (6,6)", "direction": "across", "length": 12, "group": ["24-across"], "position": {"x": 0, "y": 12}, "separatorLocations": {",": [6]}, "solution": "LETTEROPENER"}, {"id": "2-down", "number": 2, "humanNumber": "2", "clue": "Fifteenth Greek letter (7)", "direction": "down", "length": 7, "group": ["2-down"], "position": {"x": 2, "y": 0}, "separatorLocations": {}, "solution": "OMICRON"}, {"id": "3-down", "number": 3, "humanNumber": "3", "clue": "Stagger (4)", "direction": "down", "length": 4, "group": ["3-down"], "position": {"x": 4, "y": 0}, "separatorLocations": {}, "solution": "REEL"}, {"id": "4-down", "number": 4, "humanNumber": "4", "clue": "See 18", "direction": "down", "length": 6, "group": ["18-across", "4-down"], "position": {"x": 6, "y": 0}, "separatorLocations": {",": []}, "solution": "SAVING"}, {"id": "5-down", "number": 5, "humanNumber": "5", "clue": "See 14", "direction": "down", "length": 8, "group": ["14-across", "5-down"], "position": {"x": 8, "y": 0}, "separatorLocations": {"-": []}, "solution": "TWISTERS"}, {"id": "6-down", "number": 6, "humanNumber": "6", "clue": "Female English singer-songwriter, b. 1988 (5)", "direction": "down", "length": 5, "group": ["6-down"], "position": {"x": 10, "y": 0}, "separatorLocations": {}, "solution": "ADELE"}, {"id": "7-down", "number": 7, "humanNumber": "7", "clue": "Spectacular (12)", "direction": "down", "length": 12, "group": ["7-down"], "position": {"x": 12, "y": 0}, "separatorLocations": {}, "solution": "EXTRAVAGANZA"}, {"id": "8-down", "number": 8, "humanNumber": "8", "clue": "Running lengthwise (12)", "direction": "down", "length": 12, "group": ["8-down"], "position": {"x": 0, "y": 1}, "separatorLocations": {}, "solution": "LONGITUDINAL"}, {"id": "13-down", "number": 13, "humanNumber": "13", "clue": "Disinfect with smoke (8)", "direction": "down", "length": 8, "group": ["13-down"], "position": {"x": 4, "y": 5}, "separatorLocations": {}, "solution": "FUMIGATE"}, {"id": "16-down", "number": 16, "humanNumber": "16", "clue": "Piggish (7)", "direction": "down", "length": 7, "group": ["16-down"], "position": {"x": 10, "y": 6}, "separatorLocations": {}, "solution": "PORCINE"}, {"id": "17-down", "number": 17, "humanNumber": "17", "clue": "Inexpensive and shabby (6)", "direction": "down", "length": 6, "group": ["17-down"], "position": {"x": 6, "y": 7}, "separatorLocations": {}, "solution": "CHEAPO"}, {"id": "19-down", "number": 19, "humanNumber": "19", "clue": "Leavening agent (5)", "direction": "down", "length": 5, "group": ["19-down"], "position": {"x": 2, "y": 8}, "separatorLocations": {}, "solution": "YEAST"}, {"id": "21-down", "number": 21, "humanNumber": "21", "clue": "Having considerable skill (4)", "direction": "down", "length": 4, "group": ["21-down"], "position": {"x": 8, "y": 9}, "separatorLocations": {}, "solution": "ABLE"}], "solutionAvailable": true, "dateSolutionAvailable": 1488153600000, "dimensions": {"cols": 13, "rows": 13}, "crosswordType": "quick", "pdf": "https://crosswords-static.guim.co.uk/gdn.quick.20170227.pdf", "instructions": "27 February 2017: in the clue for 18,4 across, an error has been corrected"}