{"id": "crosswords/quick/15509", "number": 15509, "name": "Quick crossword No 15,509", "date": 1579651200000, "webPublicationDate": 1579651209000, "entries": [{"id": "1-across", "number": 1, "humanNumber": "1", "clue": "Finished completely and for ever (4,3,6)", "direction": "across", "length": 13, "group": ["1-across"], "position": {"x": 0, "y": 0}, "separatorLocations": {",": [4, 7]}, "solution": "DEADANDBURIED"}, {"id": "8-across", "number": 8, "humanNumber": "8", "clue": "Nought (4)", "direction": "across", "length": 4, "group": ["8-across"], "position": {"x": 0, "y": 2}, "separatorLocations": {}, "solution": "ZERO"}, {"id": "9-across", "number": 9, "humanNumber": "9", "clue": "Maligned (8)", "direction": "across", "length": 8, "group": ["9-across"], "position": {"x": 5, "y": 2}, "separatorLocations": {}, "solution": "VILIFIED"}, {"id": "10-across", "number": 10, "humanNumber": "10", "clue": "Structure hanging from the roof of a cave (10)", "direction": "across", "length": 10, "group": ["10-across"], "position": {"x": 0, "y": 4}, "separatorLocations": {}, "solution": "STALACTITE"}, {"id": "12-across", "number": 12, "humanNumber": "12", "clue": "Baker Street detective (6)", "direction": "across", "length": 6, "group": ["12-across"], "position": {"x": 0, "y": 6}, "separatorLocations": {}, "solution": "HOLMES"}, {"id": "14-across", "number": 14, "humanNumber": "14", "clue": "Rudiments (6)", "direction": "across", "length": 6, "group": ["14-across"], "position": {"x": 7, "y": 6}, "separatorLocations": {}, "solution": "BASICS"}, {"id": "15-across", "number": 15, "humanNumber": "15", "clue": "Bad dreams (10)", "direction": "across", "length": 10, "group": ["15-across"], "position": {"x": 3, "y": 8}, "separatorLocations": {}, "solution": "NIGHTMARES"}, {"id": "19-across", "number": 19, "humanNumber": "19", "clue": "Have the idea for (8)", "direction": "across", "length": 8, "group": ["19-across"], "position": {"x": 0, "y": 10}, "separatorLocations": {}, "solution": "CONCEIVE"}, {"id": "20-across", "number": 20, "humanNumber": "20", "clue": "Publicise \u2014 stop (4)", "direction": "across", "length": 4, "group": ["20-across"], "position": {"x": 9, "y": 10}, "separatorLocations": {}, "solution": "PLUG"}, {"id": "21-across", "number": 21, "humanNumber": "21", "clue": "Able to make plants grow well (5-8)", "direction": "across", "length": 13, "group": ["21-across"], "position": {"x": 0, "y": 12}, "separatorLocations": {"-": [5]}, "solution": "GREENFINGERED"}, {"id": "2-down", "number": 2, "humanNumber": "2", "clue": "Subatomic particle \u2014 enrol etc (anag) (8)", "direction": "down", "length": 8, "group": ["2-down"], "position": {"x": 1, "y": 0}, "separatorLocations": {}, "solution": "ELECTRON"}, {"id": "3-down", "number": 3, "humanNumber": "3", "clue": "Salivate (5)", "direction": "down", "length": 5, "group": ["3-down"], "position": {"x": 3, "y": 0}, "separatorLocations": {}, "solution": "DROOL"}, {"id": "4-down", "number": 4, "humanNumber": "4", "clue": "Beginners (7)", "direction": "down", "length": 7, "group": ["4-down"], "position": {"x": 5, "y": 0}, "separatorLocations": {}, "solution": "NOVICES"}, {"id": "5-down", "number": 5, "humanNumber": "5", "clue": "Spicy Pakistani cuisine with food cooked in a karahi (5)", "direction": "down", "length": 5, "group": ["5-down"], "position": {"x": 7, "y": 0}, "separatorLocations": {}, "solution": "BALTI"}, {"id": "6-down", "number": 6, "humanNumber": "6", "clue": "Roof beams (7)", "direction": "down", "length": 7, "group": ["6-down"], "position": {"x": 9, "y": 0}, "separatorLocations": {}, "solution": "RAFTERS"}, {"id": "7-down", "number": 7, "humanNumber": "7", "clue": "Ophthalmologist's speciality (4)", "direction": "down", "length": 4, "group": ["7-down"], "position": {"x": 11, "y": 0}, "separatorLocations": {}, "solution": "EYES"}, {"id": "11-down", "number": 11, "humanNumber": "11", "clue": "Timetable (8)", "direction": "down", "length": 8, "group": ["11-down"], "position": {"x": 11, "y": 5}, "separatorLocations": {}, "solution": "SCHEDULE"}, {"id": "13-down", "number": 13, "humanNumber": "13", "clue": "Eyeglass (7)", "direction": "down", "length": 7, "group": ["13-down"], "position": {"x": 3, "y": 6}, "separatorLocations": {}, "solution": "MONOCLE"}, {"id": "14-down", "number": 14, "humanNumber": "14", "clue": "Bird that booms (7)", "direction": "down", "length": 7, "group": ["14-down"], "position": {"x": 7, "y": 6}, "separatorLocations": {}, "solution": "BITTERN"}, {"id": "16-down", "number": 16, "humanNumber": "16", "clue": "Intense sorrow (5)", "direction": "down", "length": 5, "group": ["16-down"], "position": {"x": 5, "y": 8}, "separatorLocations": {}, "solution": "GRIEF"}, {"id": "17-down", "number": 17, "humanNumber": "17", "clue": "Copious (5)", "direction": "down", "length": 5, "group": ["17-down"], "position": {"x": 9, "y": 8}, "separatorLocations": {}, "solution": "AMPLE"}, {"id": "18-down", "number": 18, "humanNumber": "18", "clue": "South African of Dutch ancestry (4)", "direction": "down", "length": 4, "group": ["18-down"], "position": {"x": 1, "y": 9}, "separatorLocations": {}, "solution": "BOER"}], "solutionAvailable": true, "dateSolutionAvailable": 1579651200000, "dimensions": {"cols": 13, "rows": 13}, "crosswordType": "quick", "pdf": "https://crosswords-static.guim.co.uk/gdn.quick.20200122.pdf"}