{"id": "crosswords/quick/10753", "number": 10753, "name": "Quick crossword No 10,753", "date": 1098403200000, "webPublicationDate": 1098399600000, "entries": [{"id": "1-across", "number": 1, "humanNumber": "1", "clue": "Cause of weakness and lack of iron (7)", "direction": "across", "length": 7, "group": ["1-across"], "position": {"x": 0, "y": 0}, "separatorLocations": {}, "solution": "ANAEMIA"}, {"id": "8-across", "number": 8, "humanNumber": "8", "clue": "Is it nature or ____? (7)", "direction": "across", "length": 7, "group": ["8-across"], "position": {"x": 6, "y": 1}, "separatorLocations": {}, "solution": "NURTURE"}, {"id": "9-across", "number": 9, "humanNumber": "9", "clue": "Cleaner found in workshop (4,3)", "direction": "across", "length": 7, "group": ["9-across"], "position": {"x": 0, "y": 2}, "separatorLocations": {",": [4]}, "solution": "OILYRAG"}, {"id": "10-across", "number": 10, "humanNumber": "10", "clue": "Amount paid all at once (4,3)", "direction": "across", "length": 7, "group": ["10-across"], "position": {"x": 6, "y": 3}, "separatorLocations": {",": [4]}, "solution": "LUMPSUM"}, {"id": "11-across", "number": 11, "humanNumber": "11", "clue": "Number (in a crowd)? (5)", "direction": "across", "length": 5, "group": ["11-across"], "position": {"x": 0, "y": 4}, "separatorLocations": {}, "solution": "THREE"}, {"id": "13-across", "number": 13, "humanNumber": "13", "clue": "Psychologically damaging (9)", "direction": "across", "length": 9, "group": ["13-across"], "position": {"x": 4, "y": 5}, "separatorLocations": {}, "solution": "TRAUMATIC"}, {"id": "15-across", "number": 15, "humanNumber": "15", "clue": "Fondness (9)", "direction": "across", "length": 9, "group": ["15-across"], "position": {"x": 0, "y": 7}, "separatorLocations": {}, "solution": "AFFECTION"}, {"id": "18-across", "number": 18, "humanNumber": "18", "clue": "Highly placed politically (2,3,7)", "direction": "across", "length": 5, "group": ["18-across", "21-across"], "position": {"x": 8, "y": 8}, "separatorLocations": {",": [2, 5]}, "solution": "INTHE"}, {"id": "21-across", "number": 21, "humanNumber": "21", "clue": "See 18", "direction": "across", "length": 7, "group": ["18-across", "21-across"], "position": {"x": 0, "y": 9}, "separatorLocations": {",": []}, "solution": "CABINET"}, {"id": "22-across", "number": 22, "humanNumber": "22", "clue": "(Piece) take(n) out (7)", "direction": "across", "length": 7, "group": ["22-across"], "position": {"x": 6, "y": 10}, "separatorLocations": {}, "solution": "EXTRACT"}, {"id": "23-across", "number": 23, "humanNumber": "23", "clue": "Vessel at sea or in kitchen (7)", "direction": "across", "length": 7, "group": ["23-across"], "position": {"x": 0, "y": 11}, "separatorLocations": {}, "solution": "STEAMER"}, {"id": "24-across", "number": 24, "humanNumber": "24", "clue": "Arctic whale (7)", "direction": "across", "length": 7, "group": ["24-across"], "position": {"x": 6, "y": 12}, "separatorLocations": {}, "solution": "NARWHAL"}, {"id": "1-down", "number": 1, "humanNumber": "1", "clue": "Take as one's own (5)", "direction": "down", "length": 5, "group": ["1-down"], "position": {"x": 0, "y": 0}, "separatorLocations": {}, "solution": "ADOPT"}, {"id": "2-down", "number": 2, "humanNumber": "2", "clue": "More gifted (5)", "direction": "down", "length": 5, "group": ["2-down"], "position": {"x": 2, "y": 0}, "separatorLocations": {}, "solution": "ABLER"}, {"id": "3-down", "number": 3, "humanNumber": "3", "clue": "System supposed to balance supply and demand (6,7)", "direction": "down", "length": 13, "group": ["3-down"], "position": {"x": 4, "y": 0}, "separatorLocations": {",": [6]}, "solution": "MARKETECONOMY"}, {"id": "4-down", "number": 4, "humanNumber": "4", "clue": "Eastern region of England (6)", "direction": "down", "length": 6, "group": ["4-down"], "position": {"x": 6, "y": 0}, "separatorLocations": {}, "solution": "ANGLIA"}, {"id": "5-down", "number": 5, "humanNumber": "5", "clue": "Leader 18 21 (5,8)", "direction": "down", "length": 13, "group": ["5-down"], "position": {"x": 8, "y": 0}, "separatorLocations": {",": [5]}, "solution": "PRIMEMINISTER"}, {"id": "6-down", "number": 6, "humanNumber": "6", "clue": "Piece of inserted material (6)", "direction": "down", "length": 6, "group": ["6-down"], "position": {"x": 10, "y": 0}, "separatorLocations": {}, "solution": "GUSSET"}, {"id": "7-down", "number": 7, "humanNumber": "7", "clue": "Relating to skin (6)", "direction": "down", "length": 6, "group": ["7-down"], "position": {"x": 12, "y": 0}, "separatorLocations": {}, "solution": "DERMIC"}, {"id": "12-down", "number": 12, "humanNumber": "12", "clue": "Short distance - steal! (4-4)", "direction": "down", "length": 4, "group": ["12-down", "14-down"], "position": {"x": 1, "y": 4}, "separatorLocations": {"-": [4]}, "solution": "HALF"}, {"id": "14-down", "number": 14, "humanNumber": "14", "clue": "See 12", "direction": "down", "length": 4, "group": ["12-down", "14-down"], "position": {"x": 11, "y": 5}, "separatorLocations": {"-": []}, "solution": "INCH"}, {"id": "15-down", "number": 15, "humanNumber": "15", "clue": "Charge (6)", "direction": "down", "length": 6, "group": ["15-down"], "position": {"x": 0, "y": 7}, "separatorLocations": {}, "solution": "ACCUSE"}, {"id": "16-down", "number": 16, "humanNumber": "16", "clue": "One who tells porkies (6)", "direction": "down", "length": 6, "group": ["16-down"], "position": {"x": 2, "y": 7}, "separatorLocations": {}, "solution": "FIBBER"}, {"id": "17-down", "number": 17, "humanNumber": "17", "clue": "Hospital doctor (US) (6)", "direction": "down", "length": 6, "group": ["17-down"], "position": {"x": 6, "y": 7}, "separatorLocations": {}, "solution": "INTERN"}, {"id": "19-down", "number": 19, "humanNumber": "19", "clue": "Instruct (5)", "direction": "down", "length": 5, "group": ["19-down"], "position": {"x": 10, "y": 8}, "separatorLocations": {}, "solution": "TEACH"}, {"id": "20-down", "number": 20, "humanNumber": "20", "clue": "Praise (5)", "direction": "down", "length": 5, "group": ["20-down"], "position": {"x": 12, "y": 8}, "separatorLocations": {}, "solution": "EXTOL"}], "solutionAvailable": true, "dateSolutionAvailable": 1098399600000, "dimensions": {"cols": 13, "rows": 13}, "crosswordType": "quick"}