{"id": "crosswords/quick/11727", "number": 11727, "name": "Quick crossword No 11,727", "date": 1196985600000, "webPublicationDate": 1196985600000, "entries": [{"id": "1-across", "number": 1, "humanNumber": "1", "clue": "Blinding vapour used to subdue (4,3)", "direction": "across", "length": 7, "group": ["1-across"], "position": {"x": 0, "y": 0}, "separatorLocations": {",": [4]}, "solution": "TEARGAS"}, {"id": "8-across", "number": 8, "humanNumber": "8", "clue": "Twister (7)", "direction": "across", "length": 7, "group": ["8-across"], "position": {"x": 6, "y": 1}, "separatorLocations": {}, "solution": "TORNADO"}, {"id": "9-across", "number": 9, "humanNumber": "9", "clue": "Sham medicine used in test or for effect (7)", "direction": "across", "length": 7, "group": ["9-across"], "position": {"x": 0, "y": 2}, "separatorLocations": {}, "solution": "PLACEBO"}, {"id": "10-across", "number": 10, "humanNumber": "10", "clue": "Of vital importance (7)", "direction": "across", "length": 7, "group": ["10-across"], "position": {"x": 6, "y": 3}, "separatorLocations": {}, "solution": "CRUCIAL"}, {"id": "11-across", "number": 11, "humanNumber": "11", "clue": "Free of dirt (5)", "direction": "across", "length": 5, "group": ["11-across"], "position": {"x": 0, "y": 4}, "separatorLocations": {}, "solution": "CLEAN"}, {"id": "13-across", "number": 13, "humanNumber": "13", "clue": "Boxer weighing 51kg or less (9)", "direction": "across", "length": 9, "group": ["13-across"], "position": {"x": 4, "y": 5}, "separatorLocations": {}, "solution": "FLYWEIGHT"}, {"id": "15-across", "number": 15, "humanNumber": "15", "clue": "Unnecessary (9)", "direction": "across", "length": 9, "group": ["15-across"], "position": {"x": 0, "y": 7}, "separatorLocations": {}, "solution": "REDUNDANT"}, {"id": "18-across", "number": 18, "humanNumber": "18", "clue": "Boring tool (5)", "direction": "across", "length": 5, "group": ["18-across"], "position": {"x": 8, "y": 8}, "separatorLocations": {}, "solution": "AUGER"}, {"id": "21-across", "number": 21, "humanNumber": "21", "clue": "Root believed to have curative properties (7)", "direction": "across", "length": 7, "group": ["21-across"], "position": {"x": 0, "y": 9}, "separatorLocations": {}, "solution": "GINSENG"}, {"id": "22-across", "number": 22, "humanNumber": "22", "clue": "Mythical horned equine (7)", "direction": "across", "length": 7, "group": ["22-across"], "position": {"x": 6, "y": 10}, "separatorLocations": {}, "solution": "UNICORN"}, {"id": "23-across", "number": 23, "humanNumber": "23", "clue": "Ineffectual (7)", "direction": "across", "length": 7, "group": ["23-across"], "position": {"x": 0, "y": 11}, "separatorLocations": {}, "solution": "USELESS"}, {"id": "24-across", "number": 24, "humanNumber": "24", "clue": "Playhouse (7)", "direction": "across", "length": 7, "group": ["24-across"], "position": {"x": 6, "y": 12}, "separatorLocations": {}, "solution": "THEATRE"}, {"id": "1-down", "number": 1, "humanNumber": "1", "clue": "Subject (5)", "direction": "down", "length": 5, "group": ["1-down"], "position": {"x": 0, "y": 0}, "separatorLocations": {}, "solution": "TOPIC"}, {"id": "2-down", "number": 2, "humanNumber": "2", "clue": "Become less intense (5)", "direction": "down", "length": 5, "group": ["2-down"], "position": {"x": 2, "y": 0}, "separatorLocations": {}, "solution": "ABATE"}, {"id": "3-down", "number": 3, "humanNumber": "3", "clue": "Having aptitude at growing plants (5-8)", "direction": "down", "length": 13, "group": ["3-down"], "position": {"x": 4, "y": 0}, "separatorLocations": {"-": [5]}, "solution": "GREENFINGERED"}, {"id": "4-down", "number": 4, "humanNumber": "4", "clue": "Thickset (6)", "direction": "down", "length": 6, "group": ["4-down"], "position": {"x": 6, "y": 0}, "separatorLocations": {}, "solution": "STOCKY"}, {"id": "5-down", "number": 5, "humanNumber": "5", "clue": "Contentious (13)", "direction": "down", "length": 13, "group": ["5-down"], "position": {"x": 8, "y": 0}, "separatorLocations": {}, "solution": "ARGUMENTATIVE"}, {"id": "6-down", "number": 6, "humanNumber": "6", "clue": "Proverb (6)", "direction": "down", "length": 6, "group": ["6-down"], "position": {"x": 10, "y": 0}, "separatorLocations": {}, "solution": "SAYING"}, {"id": "7-down", "number": 7, "humanNumber": "7", "clue": "Large handleless drinking-cup (6)", "direction": "down", "length": 6, "group": ["7-down"], "position": {"x": 12, "y": 0}, "separatorLocations": {}, "solution": "GOBLET"}, {"id": "12-down", "number": 12, "humanNumber": "12", "clue": "Enticement (4)", "direction": "down", "length": 4, "group": ["12-down"], "position": {"x": 1, "y": 4}, "separatorLocations": {}, "solution": "LURE"}, {"id": "14-down", "number": 14, "humanNumber": "14", "clue": "Enormous (4)", "direction": "down", "length": 4, "group": ["14-down"], "position": {"x": 11, "y": 5}, "separatorLocations": {}, "solution": "HUGE"}, {"id": "15-down", "number": 15, "humanNumber": "15", "clue": "Strict exactitude (6)", "direction": "down", "length": 6, "group": ["15-down"], "position": {"x": 0, "y": 7}, "separatorLocations": {}, "solution": "RIGOUR"}, {"id": "16-down", "number": 16, "humanNumber": "16", "clue": "Ass (6)", "direction": "down", "length": 6, "group": ["16-down"], "position": {"x": 2, "y": 7}, "separatorLocations": {}, "solution": "DONKEY"}, {"id": "17-down", "number": 17, "humanNumber": "17", "clue": "Dignified - month (6)", "direction": "down", "length": 6, "group": ["17-down"], "position": {"x": 6, "y": 7}, "separatorLocations": {}, "solution": "AUGUST"}, {"id": "19-down", "number": 19, "humanNumber": "19", "clue": "Apparition (5)", "direction": "down", "length": 5, "group": ["19-down"], "position": {"x": 10, "y": 8}, "separatorLocations": {}, "solution": "GHOST"}, {"id": "20-down", "number": 20, "humanNumber": "20", "clue": "Area for shooting practice (5)", "direction": "down", "length": 5, "group": ["20-down"], "position": {"x": 12, "y": 8}, "separatorLocations": {}, "solution": "RANGE"}], "solutionAvailable": true, "dateSolutionAvailable": 1196985600000, "dimensions": {"cols": 13, "rows": 13}, "crosswordType": "quick"}