{"id": "crosswords/quick/16478", "number": 16478, "name": "Quick crossword No 16,478", "date": 1677542400000, "webPublicationDate": 1677542405000, "entries": [{"id": "1-across", "number": 1, "humanNumber": "1", "clue": "M in the James Bond films (9)", "direction": "across", "length": 9, "group": ["1-across"], "position": {"x": 0, "y": 0}, "separatorLocations": {}, "solution": "SPYMASTER"}, {"id": "8-across", "number": 8, "humanNumber": "8", "clue": "First James Bond film (2,2)", "direction": "across", "length": 4, "group": ["8-across"], "position": {"x": 9, "y": 1}, "separatorLocations": {",": [2]}, "solution": "DRNO"}, {"id": "9-across", "number": 9, "humanNumber": "9", "clue": "Hot-headed (9)", "direction": "across", "length": 9, "group": ["9-across"], "position": {"x": 0, "y": 2}, "separatorLocations": {}, "solution": "IMPETUOUS"}, {"id": "10-across", "number": 10, "humanNumber": "10", "clue": "Horizontal \u2014 dull (4)", "direction": "across", "length": 4, "group": ["10-across"], "position": {"x": 9, "y": 3}, "separatorLocations": {}, "solution": "FLAT"}, {"id": "13-across", "number": 13, "humanNumber": "13", "clue": "Bookmaker's odds (5)", "direction": "across", "length": 5, "group": ["13-across"], "position": {"x": 4, "y": 4}, "separatorLocations": {}, "solution": "EVENS"}, {"id": "15-across", "number": 15, "humanNumber": "15", "clue": "Harass \u2014 pester (6)", "direction": "across", "length": 6, "group": ["15-across"], "position": {"x": 0, "y": 5}, "separatorLocations": {}, "solution": "CHIVVY"}, {"id": "16-across", "number": 16, "humanNumber": "16", "clue": "Philosophical study of morals (6)", "direction": "across", "length": 6, "group": ["16-across"], "position": {"x": 7, "y": 5}, "separatorLocations": {}, "solution": "ETHICS"}, {"id": "17-across", "number": 17, "humanNumber": "17", "clue": "Rigorous (6)", "direction": "across", "length": 6, "group": ["17-across"], "position": {"x": 0, "y": 7}, "separatorLocations": {}, "solution": "STRICT"}, {"id": "19-across", "number": 19, "humanNumber": "19", "clue": "Location of Sch\u00f6nbrunn Palace (6)", "direction": "across", "length": 6, "group": ["19-across"], "position": {"x": 7, "y": 7}, "separatorLocations": {}, "solution": "VIENNA"}, {"id": "20-across", "number": 20, "humanNumber": "20", "clue": "Shere Khan, say (5)", "direction": "across", "length": 5, "group": ["20-across"], "position": {"x": 4, "y": 8}, "separatorLocations": {}, "solution": "TIGER"}, {"id": "21-across", "number": 21, "humanNumber": "21", "clue": "Street atlas (1,2,1)", "direction": "across", "length": 4, "group": ["21-across"], "position": {"x": 0, "y": 9}, "separatorLocations": {",": [1, 3]}, "solution": "ATOZ"}, {"id": "24-across", "number": 24, "humanNumber": "24", "clue": "Study of the origin of words (9)", "direction": "across", "length": 9, "group": ["24-across"], "position": {"x": 4, "y": 10}, "separatorLocations": {}, "solution": "ETYMOLOGY"}, {"id": "25-across", "number": 25, "humanNumber": "25", "clue": "Departure (4)", "direction": "across", "length": 4, "group": ["25-across"], "position": {"x": 0, "y": 11}, "separatorLocations": {}, "solution": "EXIT"}, {"id": "26-across", "number": 26, "humanNumber": "26", "clue": "Sinner (9)", "direction": "across", "length": 9, "group": ["26-across"], "position": {"x": 4, "y": 12}, "separatorLocations": {}, "solution": "WRONGDOER"}, {"id": "2-down", "number": 2, "humanNumber": "2", "clue": "Question \u2014 shoe (4)", "direction": "down", "length": 4, "group": ["2-down"], "position": {"x": 1, "y": 0}, "separatorLocations": {}, "solution": "PUMP"}, {"id": "3-down", "number": 3, "humanNumber": "3", "clue": "Get together (4)", "direction": "down", "length": 4, "group": ["3-down"], "position": {"x": 3, "y": 0}, "separatorLocations": {}, "solution": "MEET"}, {"id": "4-down", "number": 4, "humanNumber": "4", "clue": "Illness caused by lack of Vitamin C (6)", "direction": "down", "length": 6, "group": ["4-down"], "position": {"x": 5, "y": 0}, "separatorLocations": {}, "solution": "SCURVY"}, {"id": "5-down", "number": 5, "humanNumber": "5", "clue": "Horsey (6)", "direction": "down", "length": 6, "group": ["5-down"], "position": {"x": 7, "y": 0}, "separatorLocations": {}, "solution": "EQUINE"}, {"id": "6-down", "number": 6, "humanNumber": "6", "clue": "Amazing (9)", "direction": "down", "length": 9, "group": ["6-down"], "position": {"x": 10, "y": 0}, "separatorLocations": {}, "solution": "BRILLIANT"}, {"id": "7-down", "number": 7, "humanNumber": "7", "clue": "Polaris (9)", "direction": "down", "length": 9, "group": ["7-down"], "position": {"x": 12, "y": 0}, "separatorLocations": {}, "solution": "NORTHSTAR"}, {"id": "11-down", "number": 11, "humanNumber": "11", "clue": "Tonya Harding or Nancy Kerrigan, say (3-6)", "direction": "down", "length": 9, "group": ["11-down"], "position": {"x": 0, "y": 4}, "separatorLocations": {"-": [3]}, "solution": "ICESKATER"}, {"id": "12-down", "number": 12, "humanNumber": "12", "clue": "Harsh and corrosive in tone (9)", "direction": "down", "length": 9, "group": ["12-down"], "position": {"x": 2, "y": 4}, "separatorLocations": {}, "solution": "VITRIOLIC"}, {"id": "13-down", "number": 13, "humanNumber": "13", "clue": "Kick out (5)", "direction": "down", "length": 5, "group": ["13-down"], "position": {"x": 4, "y": 4}, "separatorLocations": {}, "solution": "EVICT"}, {"id": "14-down", "number": 14, "humanNumber": "14", "clue": "Step (5)", "direction": "down", "length": 5, "group": ["14-down"], "position": {"x": 8, "y": 4}, "separatorLocations": {}, "solution": "STAIR"}, {"id": "18-down", "number": 18, "humanNumber": "18", "clue": "Giggle (6)", "direction": "down", "length": 6, "group": ["18-down"], "position": {"x": 5, "y": 7}, "separatorLocations": {}, "solution": "TITTER"}, {"id": "19-down", "number": 19, "humanNumber": "19", "clue": "Troublesome insects or rodents (6)", "direction": "down", "length": 6, "group": ["19-down"], "position": {"x": 7, "y": 7}, "separatorLocations": {}, "solution": "VERMIN"}, {"id": "22-down", "number": 22, "humanNumber": "22", "clue": "Dressed (4)", "direction": "down", "length": 4, "group": ["22-down"], "position": {"x": 9, "y": 9}, "separatorLocations": {}, "solution": "CLAD"}, {"id": "23-down", "number": 23, "humanNumber": "23", "clue": "Shivering fit (4)", "direction": "down", "length": 4, "group": ["23-down"], "position": {"x": 11, "y": 9}, "separatorLocations": {}, "solution": "AGUE"}], "solutionAvailable": true, "dateSolutionAvailable": 1677542400000, "dimensions": {"cols": 13, "rows": 13}, "crosswordType": "quick", "pdf": "https://crosswords-static.guim.co.uk/gdn.quick.20230228.pdf"}