{"id": "crosswords/quick/12025", "number": 12025, "name": "Quick crossword No 12,025", "date": 1227225600000, "webPublicationDate": 1227225600000, "entries": [{"id": "1-across", "number": 1, "humanNumber": "1", "clue": "Cookery studies etc (4,9)", "direction": "across", "length": 13, "group": ["1-across"], "position": {"x": 0, "y": 0}, "separatorLocations": {",": [4]}, "solution": "HOMEECONOMICS"}, {"id": "8-across", "number": 8, "humanNumber": "8", "clue": "Still representation of a famous person (7)", "direction": "across", "length": 7, "group": ["8-across"], "position": {"x": 0, "y": 2}, "separatorLocations": {}, "solution": "WAXWORK"}, {"id": "9-across", "number": 9, "humanNumber": "9", "clue": "Delete (5)", "direction": "across", "length": 5, "group": ["9-across"], "position": {"x": 8, "y": 2}, "separatorLocations": {}, "solution": "ERASE"}, {"id": "10-across", "number": 10, "humanNumber": "10", "clue": "Curved structure (4)", "direction": "across", "length": 4, "group": ["10-across"], "position": {"x": 0, "y": 4}, "separatorLocations": {}, "solution": "ARCH"}, {"id": "11-across", "number": 11, "humanNumber": "11", "clue": "(Chinese) dog (8)", "direction": "across", "length": 8, "group": ["11-across"], "position": {"x": 5, "y": 4}, "separatorLocations": {}, "solution": "PEKINESE"}, {"id": "13-across", "number": 13, "humanNumber": "13", "clue": "Bike with two saddles (6)", "direction": "across", "length": 6, "group": ["13-across"], "position": {"x": 0, "y": 6}, "separatorLocations": {}, "solution": "TANDEM"}, {"id": "14-across", "number": 14, "humanNumber": "14", "clue": "Oddball (6)", "direction": "across", "length": 6, "group": ["14-across"], "position": {"x": 7, "y": 6}, "separatorLocations": {}, "solution": "WEIRDO"}, {"id": "17-across", "number": 17, "humanNumber": "17", "clue": "Circulating, but unverified (8)", "direction": "across", "length": 8, "group": ["17-across"], "position": {"x": 0, "y": 8}, "separatorLocations": {}, "solution": "RUMOURED"}, {"id": "19-across", "number": 19, "humanNumber": "19", "clue": "Lip (4)", "direction": "across", "length": 4, "group": ["19-across"], "position": {"x": 9, "y": 8}, "separatorLocations": {}, "solution": "EDGE"}, {"id": "21-across", "number": 21, "humanNumber": "21", "clue": "Animal of the Andes (5)", "direction": "across", "length": 5, "group": ["21-across"], "position": {"x": 0, "y": 10}, "separatorLocations": {}, "solution": "LLAMA"}, {"id": "22-across", "number": 22, "humanNumber": "22", "clue": "Make (someone) interested and excited (7)", "direction": "across", "length": 7, "group": ["22-across"], "position": {"x": 6, "y": 10}, "separatorLocations": {}, "solution": "ENTHUSE"}, {"id": "24-across", "number": 24, "humanNumber": "24", "clue": "Football team nicknamed The Irons (4,3,6)", "direction": "across", "length": 13, "group": ["24-across"], "position": {"x": 0, "y": 12}, "separatorLocations": {",": [4, 7]}, "solution": "WESTHAMUNITED"}, {"id": "1-down", "number": 1, "humanNumber": "1", "clue": "By what means? (3)", "direction": "down", "length": 3, "group": ["1-down"], "position": {"x": 0, "y": 0}, "separatorLocations": {}, "solution": "HOW"}, {"id": "2-down", "number": 2, "humanNumber": "2", "clue": "From Chihuahua, perhaps (7)", "direction": "down", "length": 7, "group": ["2-down"], "position": {"x": 2, "y": 0}, "separatorLocations": {}, "solution": "MEXICAN"}, {"id": "3-down", "number": 3, "humanNumber": "3", "clue": "Love god (4)", "direction": "down", "length": 4, "group": ["3-down"], "position": {"x": 4, "y": 0}, "separatorLocations": {}, "solution": "EROS"}, {"id": "4-down", "number": 4, "humanNumber": "4", "clue": "Scottish island group (6)", "direction": "down", "length": 6, "group": ["4-down"], "position": {"x": 6, "y": 0}, "separatorLocations": {}, "solution": "ORKNEY"}, {"id": "5-down", "number": 5, "humanNumber": "5", "clue": "Quick quip? (3-5)", "direction": "down", "length": 8, "group": ["5-down"], "position": {"x": 8, "y": 0}, "separatorLocations": {"-": [3]}, "solution": "ONELINER"}, {"id": "6-down", "number": 6, "humanNumber": "6", "clue": "Representation (5)", "direction": "down", "length": 5, "group": ["6-down"], "position": {"x": 10, "y": 0}, "separatorLocations": {}, "solution": "IMAGE"}, {"id": "7-down", "number": 7, "humanNumber": "7", "clue": "Docker (9)", "direction": "down", "length": 9, "group": ["7-down"], "position": {"x": 12, "y": 0}, "separatorLocations": {}, "solution": "STEVEDORE"}, {"id": "10-down", "number": 10, "humanNumber": "10", "clue": "Post-sunset radiance (9)", "direction": "down", "length": 9, "group": ["10-down"], "position": {"x": 0, "y": 4}, "separatorLocations": {}, "solution": "AFTERGLOW"}, {"id": "12-down", "number": 12, "humanNumber": "12", "clue": "Leave (estate or body) (8)", "direction": "down", "length": 8, "group": ["12-down"], "position": {"x": 4, "y": 5}, "separatorLocations": {}, "solution": "BEQUEATH"}, {"id": "15-down", "number": 15, "humanNumber": "15", "clue": "Fortification (7)", "direction": "down", "length": 7, "group": ["15-down"], "position": {"x": 10, "y": 6}, "separatorLocations": {}, "solution": "REDOUBT"}, {"id": "16-down", "number": 16, "humanNumber": "16", "clue": "Regain possession in exchange for money (6)", "direction": "down", "length": 6, "group": ["16-down"], "position": {"x": 6, "y": 7}, "separatorLocations": {}, "solution": "REDEEM"}, {"id": "18-down", "number": 18, "humanNumber": "18", "clue": "Available resources (5)", "direction": "down", "length": 5, "group": ["18-down"], "position": {"x": 2, "y": 8}, "separatorLocations": {}, "solution": "MEANS"}, {"id": "20-down", "number": 20, "humanNumber": "20", "clue": "Public school (4)", "direction": "down", "length": 4, "group": ["20-down"], "position": {"x": 8, "y": 9}, "separatorLocations": {}, "solution": "ETON"}, {"id": "23-down", "number": 23, "humanNumber": "23", "clue": "Conclusion (3)", "direction": "down", "length": 3, "group": ["23-down"], "position": {"x": 12, "y": 10}, "separatorLocations": {}, "solution": "END"}], "solutionAvailable": true, "dateSolutionAvailable": 1227225600000, "dimensions": {"cols": 13, "rows": 13}, "crosswordType": "quick", "instructions": "For a printable version of this crossword click <a href=\"http://image.guardian.co.uk/sys-files/Guardian/documents/2008/11/17/Quick2111_12025.pdf\">here</a>"}