{"id": "crosswords/quick/15077", "number": 15077, "name": "Quick crossword No 15,077", "date": 1535932800000, "webPublicationDate": 1535929236000, "entries": [{"id": "1-across", "number": 1, "humanNumber": "1", "clue": "Bear of very little brain (6-3-4)", "direction": "across", "length": 13, "group": ["1-across"], "position": {"x": 0, "y": 0}, "separatorLocations": {"-": [6, 9]}, "solution": "WINNIETHEPOOH"}, {"id": "8-across", "number": 8, "humanNumber": "8", "clue": "Respiratory organ (4)", "direction": "across", "length": 4, "group": ["8-across"], "position": {"x": 0, "y": 2}, "separatorLocations": {}, "solution": "LUNG"}, {"id": "9-across", "number": 9, "humanNumber": "9", "clue": "Remorseful (8)", "direction": "across", "length": 8, "group": ["9-across"], "position": {"x": 5, "y": 2}, "separatorLocations": {}, "solution": "PENITENT"}, {"id": "10-across", "number": 10, "humanNumber": "10", "clue": "Make impure (10)", "direction": "across", "length": 10, "group": ["10-across"], "position": {"x": 0, "y": 4}, "separatorLocations": {}, "solution": "ADULTERATE"}, {"id": "12-across", "number": 12, "humanNumber": "12", "clue": "Baffles \u2014 projecting remnants (6)", "direction": "across", "length": 6, "group": ["12-across"], "position": {"x": 0, "y": 6}, "separatorLocations": {}, "solution": "STUMPS"}, {"id": "14-across", "number": 14, "humanNumber": "14", "clue": "Lab vessel (6)", "direction": "across", "length": 6, "group": ["14-across"], "position": {"x": 7, "y": 6}, "separatorLocations": {}, "solution": "RETORT"}, {"id": "15-across", "number": 15, "humanNumber": "15", "clue": "Payment (for service rendered) (10)", "direction": "across", "length": 10, "group": ["15-across"], "position": {"x": 3, "y": 8}, "separatorLocations": {}, "solution": "RECOMPENSE"}, {"id": "19-across", "number": 19, "humanNumber": "19", "clue": "Idle wanderer (8)", "direction": "across", "length": 8, "group": ["19-across"], "position": {"x": 0, "y": 10}, "separatorLocations": {}, "solution": "VAGABOND"}, {"id": "20-across", "number": 20, "humanNumber": "20", "clue": "American athlete \u2014 Scottish soldier (4)", "direction": "across", "length": 4, "group": ["20-across"], "position": {"x": 9, "y": 10}, "separatorLocations": {}, "solution": "JOCK"}, {"id": "21-across", "number": 21, "humanNumber": "21", "clue": "Pretending to be someone else (13)", "direction": "across", "length": 13, "group": ["21-across"], "position": {"x": 0, "y": 12}, "separatorLocations": {}, "solution": "IMPERSONATION"}, {"id": "2-down", "number": 2, "humanNumber": "2", "clue": "Flood (8)", "direction": "down", "length": 8, "group": ["2-down"], "position": {"x": 1, "y": 0}, "separatorLocations": {}, "solution": "INUNDATE"}, {"id": "3-down", "number": 3, "humanNumber": "3", "clue": "__ Mansell, 1992 F1 champion (5)", "direction": "down", "length": 5, "group": ["3-down"], "position": {"x": 3, "y": 0}, "separatorLocations": {}, "solution": "NIGEL"}, {"id": "4-down", "number": 4, "humanNumber": "4", "clue": "Put into words (7)", "direction": "down", "length": 7, "group": ["4-down"], "position": {"x": 5, "y": 0}, "separatorLocations": {}, "solution": "EXPRESS"}, {"id": "5-down", "number": 5, "humanNumber": "5", "clue": "Hair dye (5)", "direction": "down", "length": 5, "group": ["5-down"], "position": {"x": 7, "y": 0}, "separatorLocations": {}, "solution": "HENNA"}, {"id": "6-down", "number": 6, "humanNumber": "6", "clue": "One getting medical care (7)", "direction": "down", "length": 7, "group": ["6-down"], "position": {"x": 9, "y": 0}, "separatorLocations": {}, "solution": "PATIENT"}, {"id": "7-down", "number": 7, "humanNumber": "7", "clue": "Porcine sound (4)", "direction": "down", "length": 4, "group": ["7-down"], "position": {"x": 11, "y": 0}, "separatorLocations": {}, "solution": "OINK"}, {"id": "11-down", "number": 11, "humanNumber": "11", "clue": "Sparkling wine from Italy (8)", "direction": "down", "length": 8, "group": ["11-down"], "position": {"x": 11, "y": 5}, "separatorLocations": {}, "solution": "PROSECCO"}, {"id": "13-down", "number": 13, "humanNumber": "13", "clue": "Kent seaside resort (7)", "direction": "down", "length": 7, "group": ["13-down"], "position": {"x": 3, "y": 6}, "separatorLocations": {}, "solution": "MARGATE"}, {"id": "14-down", "number": 14, "humanNumber": "14", "clue": "Islamic fast (7)", "direction": "down", "length": 7, "group": ["14-down"], "position": {"x": 7, "y": 6}, "separatorLocations": {}, "solution": "RAMADAN"}, {"id": "16-down", "number": 16, "humanNumber": "16", "clue": "Wooden-soled shoes (5)", "direction": "down", "length": 5, "group": ["16-down"], "position": {"x": 5, "y": 8}, "separatorLocations": {}, "solution": "CLOGS"}, {"id": "17-down", "number": 17, "humanNumber": "17", "clue": "(Scottish or Irish) fool (5)", "direction": "down", "length": 5, "group": ["17-down"], "position": {"x": 9, "y": 8}, "separatorLocations": {}, "solution": "EEJIT"}, {"id": "18-down", "number": 18, "humanNumber": "18", "clue": "Old MacDonald's establishment (4)", "direction": "down", "length": 4, "group": ["18-down"], "position": {"x": 1, "y": 9}, "separatorLocations": {}, "solution": "FARM"}], "solutionAvailable": true, "dateSolutionAvailable": 1535929200000, "dimensions": {"cols": 13, "rows": 13}, "crosswordType": "quick", "pdf": "https://crosswords-static.guim.co.uk/gdn.quick.20180903.pdf"}